score_rs-0.0.1.dist-info/METADATA
score_rs-0.0.1.dist-info/WHEEL
score_rs-0.0.1.dist-info/license_files/LICENSE
score_rs/__init__.py
score_rs/score_rs.cpython-39-i386-linux-gnu.so
score_rs-0.0.1.dist-info/RECORD
