Metadata-Version: 2.1
Name: score-rs
Version: 0.0.1
Classifier: Programming Language :: Rust
Classifier: Programming Language :: Python :: Implementation :: CPython
Classifier: Programming Language :: Python :: Implementation :: PyPy
License-File: LICENSE
Home-Page: https://github.com/moldhouse/score-rs.git
Author: Moritz Althaus <moritzalthaus@gmx.de>
Author-email: Moritz Althaus <moritzalthaus@gmx.de>
License: MIT
Requires-Python: >=3.8
Project-URL: Source Code, https://github.com/moldhouse/score-rs.git
